app/__init__.py
app/core/__init__.py
app/core/api_validation/__init__.py
app/core/api_validation/api_validation.py
app/core/cache/__init__.py
app/core/cache/cache.py
app/core/config.py
app/core/context/__init__.py
app/core/context/context.py
app/core/database/__init__.py
app/core/database/database.py
app/core/health_check/__init__.py
app/core/health_check/health_check.py
app/core/http_client/__init__.py
app/core/http_client/http_client.py
app/core/logging/__init__.py
app/core/logging/logging.py
app/core/pubsub/__init__.py
app/core/pubsub/pubsub.py
app/core/rbac/__init__.py
app/core/rbac/rbac.py
app/core/security/__init__.py
app/core/security/security.py
app/core/swagger/__init__.py
app/core/swagger/swagger.py
app/core/tasks/__init__.py
app/core/tasks/tasks.py
app/crud/__init__.py
app/crud/crud.py
app/helpers/__init__.py
app/helpers/linter_formatter.py
app/main.py
app/models/__init__.py
app/models/base.py
app/models/models.py
app/routes/__init__.py
app/routes/articles.py
app/routes/authors.py
app/routes/hello.py
app/routes/ping.py
app/routes/pubsub.py
app/schemas/__init__.py
app/schemas/schemas.py
app/utils/__init__.py
app/utils/authentication.py
app/utils/database.py
app/utils/redis.py
app/utils/settings.py
abl_library-0.1.0.dist-info/METADATA
abl_library-0.1.0.dist-info/WHEEL
abl_library-0.1.0.dist-info/RECORD
